pyqcircuit/__init__.py
pyqcircuit/graphics_target.py
pyqcircuit/matplotlib_backend.py
pyqcircuit/primitives.py
pyqcircuit/quantum_circuit.py
pyqcircuit/renderers.py
pyqcircuit/style.py
pyqcircuit/version.py
pyqcircuit-0.3.0.dist-info/licenses/LICENSE
pyqcircuit-0.3.0.dist-info/METADATA
pyqcircuit-0.3.0.dist-info/WHEEL
pyqcircuit-0.3.0.dist-info/top_level.txt
pyqcircuit-0.3.0.dist-info/RECORD
