Metadata-Version: 2.4
Name: pyqcircuit
Version: 0.3.0
Author: Damien Crielaard
License: The Clear BSD License
Classifier: Intended Audience :: Science/Research
Classifier: License :: OSI Approved :: BSD License
Classifier: Programming Language :: Python :: 3
Classifier: Programming Language :: Python :: 3.11
Classifier: Programming Language :: Python :: 3.12
Classifier: Programming Language :: Python :: 3.13
Classifier: Topic :: Scientific/Engineering :: Quantum Computing
Requires-Python: >=3.11
License-File: LICENSE
Requires-Dist: numpy
Requires-Dist: matplotlib
Provides-Extra: dev
Requires-Dist: ruff; extra == "dev"
Requires-Dist: mypy<2.0,>=1.0; extra == "dev"
Requires-Dist: black<25.0,>=23.0; extra == "dev"
Requires-Dist: isort<5.14,>=5.12; extra == "dev"
Requires-Dist: pytest; extra == "dev"
Requires-Dist: pytest-sphinx; extra == "dev"
Requires-Dist: pytest-cov; extra == "dev"
Requires-Dist: twine>=1.11.0; extra == "dev"
Requires-Dist: build; extra == "dev"
Requires-Dist: setuptools; extra == "dev"
Requires-Dist: wheel; extra == "dev"
Requires-Dist: Sphinx<9.0,>=6.0; extra == "dev"
Requires-Dist: furo==2024.8.6; extra == "dev"
Requires-Dist: myst-parser>=1.0; extra == "dev"
Requires-Dist: sphinx-copybutton; extra == "dev"
Requires-Dist: sphinx-autobuild; extra == "dev"
Requires-Dist: sphinx-autodoc-typehints==1.23.3; extra == "dev"
Requires-Dist: packaging; extra == "dev"
Dynamic: license-file
